patlang.py
patlang-0.0.3.dist-info/licenses/LICENSE
patlang-0.0.3.dist-info/licenses/NOTICE
patlang-0.0.3.dist-info/METADATA
patlang-0.0.3.dist-info/WHEEL
patlang-0.0.3.dist-info/top_level.txt
patlang-0.0.3.dist-info/RECORD
