Metadata-Version: 2.4
Name: patlang
Version: 0.0.3
Summary: pattern language
Author-email: MarijnvTricht <marijnpy@gmx.com>
Project-URL: Homepage, https://github.com/MarijnvanTricht/patlang
Project-URL: Issues, https://github.com/MarijnvanTricht/patlang
Classifier: Programming Language :: Python :: 3
Classifier: Operating System :: OS Independent
Requires-Python: >=3.8
License-File: LICENSE
License-File: NOTICE
Dynamic: license-file
